pep2google/__init__.py
pep2google/parser.py
sphinx2doxygen-0.1.data/scripts/sphinx2doxygen
sphinx2doxygen-0.1.dist-info/LICENSE
sphinx2doxygen-0.1.dist-info/METADATA
sphinx2doxygen-0.1.dist-info/WHEEL
sphinx2doxygen-0.1.dist-info/top_level.txt
sphinx2doxygen-0.1.dist-info/RECORD
