Metadata-Version: 2.1
Name: sphinx2doxygen
Version: 0.1
Summary: Rewrites python documentation string code commenting from Sphinx to Doxygen format.
Home-page: https://github.com/br-olf/sphinx2doxygen
Author: Brolf
Author-email: brolf@magheute.net
License: EUPL-1.2
Keywords: PEP,convert,Doxygen,Google
Platform: UNKNOWN
Classifier: Programming Language :: Python :: 3
Classifier: License :: OSI Approved :: European Union Public Licence 1.2 (EUPL 1.2)
Classifier: Operating System :: OS Independent
Classifier: Environment :: Console
Classifier: Intended Audience :: Developers
Classifier: Natural Language :: English
Classifier: Topic :: Software Development :: Documentation
Classifier: Development Status :: 3 - Alpha
Requires-Python: >=3.6
